Workbook

Sheet Supuestos
A1: GRANKHA · Supuestos de cálculo
A2: Edita solo las celdas amarillas de la columna B. El resto se recalcula.
A4: Concepto | B4: Valor | C4: Nota
A5: IVA español aplicado (península y Baleares) | B5: 0.21 | C5: Canarias, Ceuta y Melilla: sin IVA (IGIC/IPSI se liquida en destino).
A6: Comisión Stripe (tarjeta europea) | B6: 0.015 | C6: Stripe España: 1,5 % + 0,25 € en tarjetas europeas.
A7: Comisión fija Stripe por transacción | B7: 0.25
A8: Coste de envío del proveedor (tarifa real AW, por pedido) | B8: 2.95 | C8: VERIFICADO en aw-dropship.es/shipping (15/10/2026): 2,95 € hasta 1 kg · 4,00 € de 1 a 5 kg · 6,50 € más de 5 kg. Sin IVA (deducible).
A9: Coste de embalaje / manipulación por pedido | B9: 0.6
A10: % de beneficios destinado a investigación | B10: 0.05 | C10: Compromiso GRANKHA: se reserva sobre los beneficios.
A11: Devoluciones previstas (sobre ventas) | B11: 0.04 | C11: Estimación; ajústala con datos reales.
A12: Coste medio de una devolución | B12: 9 | C12: Transporte de retorno + gestión.
A13: Coste de adquisición de cliente (CAC objetivo) | B13: 6 | C13: Publicidad media por cliente nuevo (Meta/Google/TikTok).
A15: Costes fijos mensuales
A16: Concepto | B16: €/mes
A17: Supabase + dominio + herramientas | B17: 25
A18: Gestoría, tasas y otros | B18: 40
A19: TOTAL costes fijos | B19: =SUM(B17:B18)

Sheet Margen por producto
A1: Beneficio real por unidad (1 ud. por pedido, envío del proveedor repartido)
A2: El PVP incluye IVA: el ingreso neto es PVP / (1 + IVA). Revisa tus precios con estos datos.
A4: SKU | B4: Producto | C4: Variante | D4: Categoría | E4: Peso (g) | F4: Coste proveedor | G4: PVP (IVA incl.) | H4: IVA incluido | I4: Ingreso neto | J4: Comisión Stripe | K4: Envío proveedor | L4: Embalaje | M4: Prov. devoluciones | N4: Donación investigación | O4: BENEFICIO NETO | P4: Margen s/ingreso neto
A5: PAWH-01 | B5: Arnés de paso Guardian | C5: XS (2-4 kg) · Rosa suave · Cuarzo rosa | D5: Arneses | E5: 110 | F5: 18.63 | G5: 36.9 | H5: =G5-G5/(1+Supuestos!$B$5) | I5: =G5/(1+Supuestos!$B$5) | J5: =-G5*Supuestos!$B$6-Supuestos!$B$7 | K5: =-Supuestos!$B$8 | L5: =-Supuestos!$B$9 | M5: =-Supuestos!$B$11*Supuestos!$B$12 | N5: =-I5*Supuestos!$B$10 | O5: =-F5+I5+J5+K5+L5+M5+N5 | P5: =IF(I5=0,0,O5/I5)
A6: PAWH-02 | B6: Arnés de paso Guardian | C6: XS (2-4 kg) · Lavanda · Amatista | D6: Arneses | E6: 110 | F6: 18.63 | G6: 36.9 | H6: =G6-G6/(1+Supuestos!$B$5) | I6: =G6/(1+Supuestos!$B$5) | J6: =-G6*Supuestos!$B$6-Supuestos!$B$7 | K6: =-Supuestos!$B$8 | L6: =-Supuestos!$B$9 | M6: =-Supuestos!$B$11*Supuestos!$B$12 | N6: =-I6*Supuestos!$B$10 | O6: =-F6+I6+J6+K6+L6+M6+N6 | P6: =IF(I6=0,0,O6/I6)
A7: PAWH-03 | B7: Arnés de paso Guardian | C7: XS (2-4 kg) · Rock Grey · Obsidiana negra | D7: Arneses | E7: 110 | F7: 18.63 | G7: 36.9 | H7: =G7-G7/(1+Supuestos!$B$5) | I7: =G7/(1+Supuestos!$B$5) | J7: =-G7*Supuestos!$B$6-Supuestos!$B$7 | K7: =-Supuestos!$B$8 | L7: =-Supuestos!$B$9 | M7: =-Supuestos!$B$11*Supuestos!$B$12 | N7: =-I7*Supuestos!$B$10 | O7: =-F7+I7+J7+K7+L7+M7+N7 | P7: =IF(I7=0,0,O7/I7)
A8: PAWH-04 | B8: Arnés de paso Guardian | C8: S (4-8 kg) · Rosa suave · Cuarzo rosa | D8: Arneses | E8: 120 | F8: 18.63 | G8: 36.9 | H8: =G8-G8/(1+Supuestos!$B$5) | I8: =G8/(1+Supuestos!$B$5) | J8: =-G8*Supuestos!$B$6-Supuestos!$B$7 | K8: =-Supuestos!$B$8 | L8: =-Supuestos!$B$9 | M8: =-Supuestos!$B$11*Supuestos!$B$12 | N8: =-I8*Supuestos!$B$10 | O8: =-F8+I8+J8+K8+L8+M8+N8 | P8: =IF(I8=0,0,O8/I8)
A9: PAWH-05 | B9: Arnés de paso Guardian | C9: S (4-8 kg) · Lavanda · Amatista | D9: Arneses | E9: 120 | F9: 18.63 | G9: 36.9 | H9: =G9-G9/(1+Supuestos!$B$5) | I9: =G9/(1+Supuestos!$B$5) | J9: =-G9*Supuestos!$B$6-Supuestos!$B$7 | K9: =-Supuestos!$B$8 | L9: =-Supuestos!$B$9 | M9: =-Supuestos!$B$11*Supuestos!$B$12 | N9: =-I9*Supuestos!$B$10 | O9: =-F9+I9+J9+K9+L9+M9+N9 | P9: =IF(I9=0,0,O9/I9)
A10: PAWH-06 | B10: Arnés de paso Guardian | C10: S (4-8 kg) · Gris roca · Obsidiana negra | D10: Arneses | E10: 120 | F10: 18.63 | G10: 36.9 | H10: =G10-G10/(1+Supuestos!$B$5) | I10: =G10/(1+Supuestos!$B$5) | J10: =-G10*Supuestos!$B$6-Supuestos!$B$7 | K10: =-Supuestos!$B$8 | L10: =-Supuestos!$B$9 | M10: =-Supuestos!$B$11*Supuestos!$B$12 | N10: =-I10*Supuestos!$B$10 | O10: =-F10+I10+J10+K10+L10+M10+N10 | P10: =IF(I10=0,0,O10/I10)
A11: PawL-07 | B11: Correa Elephant | C11: Azul · 2 m | D11: Correas | E11: 189 | F11: 18.75 | G11: 34.9 | H11: =G11-G11/(1+Supuestos!$B$5) | I11: =G11/(1+Supuestos!$B$5) | J11: =-G11*Supuestos!$B$6-Supuestos!$B$7 | K11: =-Supuestos!$B$8 | L11: =-Supuestos!$B$9 | M11: =-Supuestos!$B$11*Supuestos!$B$12 | N11: =-I11*Supuestos!$B$10 | O11: =-F11+I11+J11+K11+L11+M11+N11 | P11: =IF(I11=0,0,O11/I11)
A12: PawL-08 | B12: Correa Elephant | C12: Marrón · 2 m | D12: Correas | E12: 189 | F12: 18.75 | G12: 34.9 | H12: =G12-G12/(1+Supuestos!$B$5) | I12: =G12/(1+Supuestos!$B$5) | J12: =-G12*Supuestos!$B$6-Supuestos!$B$7 | K12: =-Supuestos!$B$8 | L12: =-Supuestos!$B$9 | M12: =-Supuestos!$B$11*Supuestos!$B$12 | N12: =-I12*Supuestos!$B$10 | O12: =-F12+I12+J12+K12+L12+M12+N12 | P12: =IF(I12=0,0,O12/I12)
A13: PawL-09 | B13: Correa Elephant | C13: Gris · 2 m | D13: Correas | E13: 189 | F13: 18.75 | G13: 34.9 | H13: =G13-G13/(1+Supuestos!$B$5) | I13: =G13/(1+Supuestos!$B$5) | J13: =-G13*Supuestos!$B$6-Supuestos!$B$7 | K13: =-Supuestos!$B$8 | L13: =-Supuestos!$B$9 | M13: =-Supuestos!$B$11*Supuestos!$B$12 | N13: =-I13*Supuestos!$B$10 | O13: =-F13+I13+J13+K13+L13+M13+N13 | P13: =IF(I13=0,0,O13/I13)
A14: PawL-04 | B14: Correa Mini Mango | C14: Amarillo · 3 m | D14: Correas | E14: 122 | F14: 15.75 | G14: 29.9 | H14: =G14-G14/(1+Supuestos!$B$5) | I14: =G14/(1+Supuestos!$B$5) | J14: =-G14*Supuestos!$B$6-Supuestos!$B$7 | K14: =-Supuestos!$B$8 | L14: =-Supuestos!$B$9 | M14: =-Supuestos!$B$11*Supuestos!$B$12 | N14: =-I14*Supuestos!$B$10 | O14: =-F14+I14+J14+K14+L14+M14+N14 | P14: =IF(I14=0,0,O14/I14)
A15: PawL-05 | B15: Correa Mini Mango | C15: Ciruela · 3 m | D15: Correas | E15: 122 | F15: 15.75 | G15: 29.9 | H15: =G15-G15/(1+Supuestos!$B$5) | I15: =G15/(1+Supuestos!$B$5) | J15: =-G15*Supuestos!$B$6-Supuestos!$B$7 | K15: =-Supuestos!$B$8 | L15: =-Supuestos!$B$9 | M15: =-Supuestos!$B$11*Supuestos!$B$12 | N15: =-I15*Supuestos!$B$10 | O15: =-F15+I15+J15+K15+L15+M15+N15 | P15: =IF(I15=0,0,O15/I15)
A16: PawL-06 | B16: Correa Mini Mango | C16: Durazno · 3 m | D16: Correas | E16: 122 | F16: 15.75 | G16: 29.9 | H16: =G16-G16/(1+Supuestos!$B$5) | I16: =G16/(1+Supuestos!$B$5) | J16: =-G16*Supuestos!$B$6-Supuestos!$B$7 | K16: =-Supuestos!$B$8 | L16: =-Supuestos!$B$9 | M16: =-Supuestos!$B$11*Supuestos!$B$12 | N16: =-I16*Supuestos!$B$10 | O16: =-F16+I16+J16+K16+L16+M16+N16 | P16: =IF(I16=0,0,O16/I16)
... A48: PACK-05 | B48: Pack Hogar Real | C48: Pack de 2 piezas | D48: Packs | E48: 2020 | F48: 42.75 | G48: 84.9 | H48: =G48-G48/(1+Supuestos!$B$5) | I48: =G48/(1+Supuestos!$B$5) | J48: =-G48*Supuestos!$B$6-Supuestos!$B$7 | K48: =-Supuestos!$B$8 | L48: =-Supuestos!$B$9 | M48: =-Supuestos!$B$11*Supuestos!$B$12 | N48: =-I48*Supuestos!$B$10 | O48: =-F48+I48+J48+K48+L48+M48+N48 | P48: =IF(I48=0,0,O48/I48)
N50: Beneficio medio | O50: =AVERAGE(O5:O48)
N51: Margen medio | O51: =AVERAGE(P5:P48)
B53: Nota: si un producto tiene beneficio negativo, súbelo de precio o retíralo. Los artículos de bajo importe suelen necesitar venta cruzada (2-3 uds. por pedido) para compensar el coste fijo del envío y de Stripe.

Sheet Pedido ejemplo
A1: Cuenta de resultados de un pedido tipo
A2: Edita cantidades y el envío cobrado (amarillo).
A4: Producto | B4: Cantidad | C4: PVP ud. (IVA incl.) | D4: Coste ud. | E4: Subtotal venta | F4: Coste total
A5: PAWH-01 · Arnés de paso Guardian · XS (2-4 kg) · Rosa suave · Cuarzo rosa | B5: 1 | C5: 36.9 | D5: 18.63 | E5: =B5*C5 | F5: =B5*D5
A6: PawL-01 · Correa Pocket Pod · Rosa · 1,5 m | B6: 1 | C6: 21.9 | D6: 12 | E6: =B6*C6 | F6: =B6*D6
A7: PAWFB-01 · Comedero estilo cobre · Ø 18 cm · Acero inoxidable 304 | B7: 1 | C7: 13.9 | D7: 4.5 | E7: =B7*C7 | F7: =B7*D7
D8: Subtotal (IVA incl.) | E8: =SUM(E5:E7) | F8: =SUM(F5:F7)
D9: Envío cobrado al cliente | E9: 5.95
D10: TOTAL COBRADO | E10: =E8+E9
A12: Cuenta de resultados
A13: Ingresos (venta sin IVA) | B13: =E8/(1+Supuestos!$B$5)
A14: Envío cobrado al cliente | B14: =E9
A15: Coste de los productos | B15: =-F8
A16: Envío pagado al proveedor | B16: =-Supuestos!$B$8
A17: Embalaje / manipulación | B17: =-Supuestos!$B$9
A18: Comisión Stripe | B18: =-E10*Supuestos!$B$6-Supuestos!$B$7
A19: Provisión devoluciones | B19: =-Supuestos!$B$11*Supuestos!$B$12
A20: Donación a investigación | B20: =-E8/(1+Supuestos!$B$5)*Supuestos!$B$10
A21: BENEFICIO DEL PEDIDO | B21: =SUM(B13:B20)
A22: Margen sobre ventas sin IVA | B22: =B21/(E8/(1+Supuestos!$B$5))
A24: Variante: el pedido supera el envío gratis (tú pagas el envío del cliente) | B24: =B21-E9
A26: Usa esta hoja para decidir el umbral de envío gratis: comprueba qué queda en el bolsillo cuando lo asumes tú, y cuánto sube el ticket medio por la venta cruzada.

Sheet Punto de equilibrio
A1: ¿Cuántas ventas necesito al mes?
A2: Basado en el beneficio del pedido ejemplo (hoja anterior).
A4: Beneficio por pedido (ejemplo) | B4: ='Pedido ejemplo'!B21
A5: Costes fijos mensuales | B5: =Supuestos!$B$19
A6: Pedidos/mes para cubrir costes fijos | B6: =IF(B4<=0,"—",B5/B4)
A7: CAC objetivo por cliente | B7: =Supuestos!$B$13
A8: Pedidos/mes para cubrir fijos + CAC | B8: =IF(B4<=B7,"—",B5/(B4-B7))
A9: Ejemplo: 100 pedidos/mes (beneficio antes de fijos) | B9: =100*(B4-B7)-B5
A10: Ejemplo: 250 pedidos/mes (beneficio antes de fijos) | B10: =250*(B4-B7)-B5
A12: Si el beneficio por pedido es menor que el CAC, cada venta pierde dinero: sube el ticket medio (packs de arnés + correa, envío gratis desde 49 €) o mejora el margen negociando precios con el proveedor.
